pelc/__init__.py
pelc/_input_sanity_check.py
pelc/_open_epregistry_databases.py
pelc/_unexpected_alleles.py
pelc/batch_eplet_comp.py
pelc/batch_eplet_comp_aux.py
pelc/data/A.csv
pelc/data/A_False_A_.pickle
pelc/data/A_True_A_.pickle
pelc/data/B.csv
pelc/data/B_False_B_.pickle
pelc/data/B_True_B_.pickle
pelc/data/C.csv
pelc/data/C_False_C_.pickle
pelc/data/C_True_C_.pickle
pelc/data/DP.csv
pelc/data/DP_False_DPB1_.pickle
pelc/data/DP_True_DPB1_.pickle
pelc/data/DQ.csv
pelc/data/DQ_False_DQB1_.pickle
pelc/data/DQ_True_DQB1_.pickle
pelc/data/DR.csv
pelc/data/DR_False_DRB1_.pickle
pelc/data/DR_True_DRB1_.pickle
pelc/data/ep_data.csv
pelc/data/ep_data.pickle
pelc/output_type.py
pelc/simple_comparison.py
pelc-0.5.4.4.dist-info/METADATA
pelc-0.5.4.4.dist-info/WHEEL
pelc-0.5.4.4.dist-info/RECORD
