Metadata-Version: 2.3
Name: pelc
Version: 0.5.4.4
Summary: Python Eplet Load Calculator
Author: JasonMendoza2008
Author-email: lhotteromain@gmail.com
Requires-Python: >=3.10,<4.0
Classifier: Programming Language :: Python :: 3
Classifier: Programming Language :: Python :: 3.10
Classifier: Programming Language :: Python :: 3.11
Classifier: Programming Language :: Python :: 3.12
Classifier: Programming Language :: Python :: 3.13
Requires-Dist: openpyxl (>=3.0.10,<4.0.0)
Requires-Dist: pandas (>=2.1.0,<3.0.0)
Requires-Dist: pandas-stubs (>=2.1.4.231227,<3.0.0.0)
